yaapp/__init__.py
yaapp/app.py
yaapp/async_compat.py
yaapp/config.py
yaapp/config_node.py
yaapp/context_tree.py
yaapp/core.py
yaapp/discovery.py
yaapp/execution_strategy.py
yaapp/expose.py
yaapp/reflection.py
yaapp/result.py
yaapp/run.py
yaapp/exposers/__init__.py
yaapp/exposers/base.py
yaapp/exposers/base_uniform_interface.py
yaapp/exposers/class_exposer.py
yaapp/exposers/class_exposer_uniform_interface.py
yaapp/exposers/custom.py
yaapp/exposers/function.py
yaapp/exposers/object.py
yaapp/plugins/__init__.py
yaapp/plugins/calculator/__init__.py
yaapp/plugins/calculator/plugin.py
yaapp/runners/__init__.py
yaapp/runners/click/__init__.py
yaapp/runners/click/runner.py
yaapp_core-0.0.40.dist-info/licenses/LICENSE
yaapp_core-0.0.40.dist-info/METADATA
yaapp_core-0.0.40.dist-info/WHEEL
yaapp_core-0.0.40.dist-info/entry_points.txt
yaapp_core-0.0.40.dist-info/top_level.txt
yaapp_core-0.0.40.dist-info/RECORD
